ncbi_taxid/__init__.py
ncbi_taxid/cli.py
ncbi_taxid/taxid_utils.py
ncbi_taxid-0.1.0.dist-info/entry_points.txt
ncbi_taxid-0.1.0.dist-info/WHEEL
ncbi_taxid-0.1.0.dist-info/METADATA
ncbi_taxid-0.1.0.dist-info/RECORD
